qlk_test_Liat/__init__.py
qlk_test_liat-0.1.0.dist-info/METADATA
qlk_test_liat-0.1.0.dist-info/WHEEL
qlk_test_liat-0.1.0.dist-info/RECORD
